{
	"required": true,
	"minVersion": "0.8",
	"package": "com.github.theredbrain.rpginventory.mixin",
	"compatibilityLevel": "JAVA_21",
	"mixins": [
		"entity.LivingEntityMixin",
		"entity.attribute.EntityAttributesMixin",
		"entity.player.PlayerEntityMixin",
		"entity.player.PlayerInventoryMixin",
		"item.ItemMixin",
		"item.ItemStackMixin",
		"screen.ArmorSlotMixin",
		"screen.PlayerScreenHandlerMixin",
		"screen.PlayerScreenHandlerOffHandSlotMixin",
		"screen.SlotMixin",
		"server.network.EntityTrackerEntryMixin",
		"server.network.ServerPlayerEntityMixin",
		"server.network.ServerPlayNetworkHandlerMixin",
		"trinkets.SurvivalTrinketSlotMixin",
		"trinkets.TrinketScreenManagerMixin"
	],
	"injectors": {
		"defaultRequire": 1
	},
	"client": [
		"client.gui.hud.InGameHudMixin",
		"client.gui.screen.ingame.CreativeInventoryScreenMixin",
		"client.gui.screen.ingame.HandledScreenMixin",
		"client.gui.screen.ingame.InventoryScreenMixin",
		"client.render.entity.PlayerEntityRendererMixin"
	]
}
